{
  "chainId": "bwarelabs_1922608-1",
  "chainName": "Bware Labs",
  "rpc": "http://142.132.132.164:36657",
  "rest": "http://142.132.132.164:31317",
  "bech32Prefix": "ethm",
  "currencies": [
    {
      "displayDenom": "bwr",
      "baseDenom": "ubwr",
      "decimals": 18,
      "logo": "/logos/bwarelabs_1922608-1.svg",
      "type": "main"
    }
  ],
  "coinType": 60,
  "faucetUrl": "https://discord.com/channels/956961633165529098/1143231362468434022",
  "website": "",
  "logo": "/logos/bwarelabs_1922608-1.svg",
  "ibc": {
    "hubChannel": "channel-6514",
    "channel": "channel-0",
    "timeout": 172800000
  },
  "evm": {
    "chainId": "0x1d5630",
    "rpc": "http://142.132.132.164:9545"
  },
  "type": "RollApp",
  "da": "Celestia",
  "description": "",
  "analytics": true,
  "validator": true
}
