
{
  "chainId": "myrollerapp_4555277-1",
  "chainName": "myrollerapp_4555277-1",
  "rpc": "http://109.123.253.67:26657",
  "rest": "http://109.123.253.67:1317",
  "bech32Prefix": "ethm",
  "currencies": [
    {
      "displayDenom": "bbu",
      "baseDenom": "ubbu",
      "decimals": 18,
      "logo": "/logos/myrollerapp_4555277-1.png",
      "type": "main"
    }
  ],
  "coinType": 60,
  "faucetUrl": "https://discord.com/channels/956961633165529098/1125047988247593010",
  "website": "",
  "logo": "/logos/myrollerapp_4555277-1.png",
  "ibc": {
    "hubChannel": "channel-5420",
    "channel": "channel-0",
    "timeout": 172800000
  },
  "evm": {
    "chainId": "0x45820d",
    "rpc": "http://109.123.253.67.8545"
  },
  "type": "RollApp",
  "da": "Celestia",
  "description": "",
  "analytics": true
}
