{ "chainId": "ara_7781166-1", "chainName": "Aranodes", "rpc": 
  "http://159.223.34.107:26657", "rest": "http://159.223.34.107:1317", 
  "bech32Prefix": "ethm", "currencies": [
    { "displayDenom": "ARA", "baseDenom": "uARA", "decimals": 18, 
      "logo": "/logos/ara_7781166-1.jpg", "type": "main"
    }
  ], "coinType": 60, "faucetUrl": 
  "https://discord.com/channels/956961633165529098/1143231362468434022", 
  "website": "", "logo": "/logos/ara_7781166-1.jpg", "ibc": {
    "hubChannel": "channel-6289", "channel": "channel-0", "timeout": 
    172800000
  },
  "evm": { "chainId": "0x8e7123", "rpc": ""
  },
  "type": "RollApp", "da": "Celestia", "description": "", "analytics": 
  true
}
